gitstats/__init__.py
gitstats/get_stats.py
gitstats/repo_metrics.py
gitstats_py-1.0.5.dist-info/LICENSE.md
gitstats_py-1.0.5.dist-info/METADATA
gitstats_py-1.0.5.dist-info/WHEEL
gitstats_py-1.0.5.dist-info/entry_points.txt
gitstats_py-1.0.5.dist-info/top_level.txt
gitstats_py-1.0.5.dist-info/zip-safe
gitstats_py-1.0.5.dist-info/RECORD
