Metadata-Version: 2.1
Name: gitstats-py
Version: 1.0.5
Summary: This library gives you some user metrics in batch from a set of github repositories.
Author: Pablo Pazo Jiménez
Author-email: ppazo@us.es
License: GNU General Public License v3 (GPLv3)
Classifier: Programming Language :: Python :: 3
Classifier: License :: OSI Approved :: GNU General Public License v3 (GPLv3)
Classifier: Operating System :: OS Independent
Requires-Python: >=3.0
License-File: LICENSE.md
Requires-Dist: PyGithub
Requires-Dist: gitpython
